llama_index/llms/oci_genai/__init__.py
llama_index/llms/oci_genai/base.py
llama_index/llms/oci_genai/utils.py
llama_index_llms_oci_genai-0.6.3.dist-info/METADATA
llama_index_llms_oci_genai-0.6.3.dist-info/WHEEL
llama_index_llms_oci_genai-0.6.3.dist-info/licenses/LICENSE
llama_index_llms_oci_genai-0.6.3.dist-info/RECORD
