Metadata-Version: 2.4
Name: llama-index-llms-oci-genai
Version: 0.6.3
Summary: llama-index llms OCI GenAI integration
Author-email: Arthur Cheng <arthur.cheng@oracle.com>, Pan Xia <pan.xia@oracle.com>, Rave Harpaz <rave.harpaz@oracle.com>
License-Expression: MIT
License-File: LICENSE
Requires-Python: <4.0,>=3.9
Requires-Dist: llama-index-core<0.15,>=0.13.0
Requires-Dist: oci<3,>=2.134.0
